.gitignore
LICENSE
MANIFEST.in
README.md
makerpm.sh
setup.py
apachekerbauth/etc/httpd/conf.d/swift-auth.conf
apachekerbauth/var/www/cgi-bin/swift-auth
doc/architecture.md
doc/ipa_client.md
doc/ipa_server.md
doc/swiftkerbauth_guide.md
swiftkerbauth/__init__.py
swiftkerbauth/kerbauth.py
swiftkerbauth.egg-info/PKG-INFO
swiftkerbauth.egg-info/SOURCES.txt
swiftkerbauth.egg-info/dependency_links.txt
swiftkerbauth.egg-info/entry_points.txt
swiftkerbauth.egg-info/requires.txt
swiftkerbauth.egg-info/top_level.txt