Metadata-Version: 1.1
Name: swiftkerbauth
Version: 1.0.1
Summary: Kerberos authentication filter for Openstack Swift
Home-page: https://forge.gluster.org/swiftkerbauth
Author: Red Hat, Inc.
Author-email: gluster-users@gluster.org
License: Apache License (2.0)
Keywords: openstack swift kerberos
Platform: UNKNOWN
Classifier: Development Status :: 3 - Alpha
Classifier: Environment :: OpenStack
Classifier: Intended Audience :: Information Technology
Classifier: Intended Audience :: System Administrators
Classifier: License :: OSI Approved :: Apache Software License
Classifier: Operating System :: POSIX :: Linux
Classifier: Programming Language :: Python
Classifier: Programming Language :: Python :: 2
Classifier: Programming Language :: Python :: 2.6
Classifier: Programming Language :: Python :: 2.7
